fubular/__init__.py
fubular/pipelines.py
fast_tubular-0.0.0.dist-info/METADATA
fast_tubular-0.0.0.dist-info/WHEEL
fast_tubular-0.0.0.dist-info/top_level.txt
fast_tubular-0.0.0.dist-info/RECORD
