Metadata-Version: 2.1
Name: fast-tubular
Version: 0.0.0
Summary: fast-tubular package
Home-page: UNKNOWN
License: MIT
Platform: UNKNOWN
Classifier: License :: OSI Approved :: MIT License
Classifier: Programming Language :: Python :: 3
Classifier: Programming Language :: Python :: 3.7
